OpenREM-0.10.0.data/scripts/openrem_ctphilips.py
OpenREM-0.10.0.data/scripts/openrem_cttoshiba.py
OpenREM-0.10.0.data/scripts/openrem_dx.py
OpenREM-0.10.0.data/scripts/openrem_mg.py
OpenREM-0.10.0.data/scripts/openrem_ptsizecsv.py
OpenREM-0.10.0.data/scripts/openrem_qr.py
OpenREM-0.10.0.data/scripts/openrem_rdsr.py
OpenREM-0.10.0.data/scripts/openrem_store.py
openrem/__init__.py
openrem/manage.py
openrem/openremproject/__init__.py
openrem/openremproject/celeryapp.py
openrem/openremproject/local_settings.py.example
openrem/openremproject/settings.py
openrem/openremproject/urls.py
openrem/openremproject/wsgi.py.example
openrem/remapp/__init__.py
openrem/remapp/admin.py
openrem/remapp/forms.py
openrem/remapp/models.py
openrem/remapp/tasks.py
openrem/remapp/urls.py
openrem/remapp/version.py
openrem/remapp/views.py
openrem/remapp/exports/__init__.py
openrem/remapp/exports/ct_export.py
openrem/remapp/exports/dx_export.py
openrem/remapp/exports/export_common.py
openrem/remapp/exports/exportviews.py
openrem/remapp/exports/mg_csv_nhsbsp.py
openrem/remapp/exports/mg_export.py
openrem/remapp/exports/rf_export.py
openrem/remapp/extractors/__init__.py
openrem/remapp/extractors/ct_philips.py
openrem/remapp/extractors/ct_toshiba.py
openrem/remapp/extractors/dx.py
openrem/remapp/extractors/extract_common.py
openrem/remapp/extractors/mam.py
openrem/remapp/extractors/ptsizecsv2db.py
openrem/remapp/extractors/rdsr.py
openrem/remapp/interface/__init__.py
openrem/remapp/interface/chart_functions.py
openrem/remapp/interface/mod_filters.py
openrem/remapp/migrations/0002_0_7_fresh_install_add_median.py.inactive
openrem/remapp/migrations/__init__.py
openrem/remapp/netdicom/__init__.py
openrem/remapp/netdicom/dicomviews.py
openrem/remapp/netdicom/keepalive.py
openrem/remapp/netdicom/qrscu.py
openrem/remapp/netdicom/storescp.py
openrem/remapp/netdicom/storescu.py
openrem/remapp/netdicom/tools.py
openrem/remapp/static/css/bootstrap-theme.css
openrem/remapp/static/css/bootstrap-theme.css.map
OpenREM-0.10.0.dist-info/COPYING-GPLv3
OpenREM-0.10.0.dist-info/LICENSE
OpenREM-0.10.0.dist-info/METADATA
OpenREM-0.10.0.dist-info/WHEEL
OpenREM-0.10.0.dist-info/top_level.txt
OpenREM-0.10.0.dist-info/RECORD
