Metadata-Version: 2.1
Name: OpenREM
Version: 0.10.0
Summary: Open source patient radiation dose monitoring software
Home-page: https://openrem.org/
Author: Ed McDonagh
Author-email: ed@openrem.org
License: GPLv3 with additional permissions
Platform: UNKNOWN
Classifier: Environment :: Web Environment
Classifier: Framework :: Django
Classifier: Intended Audience :: Healthcare Industry
Classifier: License :: OSI Approved :: GNU General Public License v3 or later (GPLv3+)
Classifier: Operating System :: OS Independent
Classifier: Programming Language :: Python
Classifier: Programming Language :: Python :: 2 :: Only
Classifier: Programming Language :: Python :: 2.7
Classifier: Topic :: Scientific/Engineering :: Medical Science Apps.
Classifier: Topic :: Scientific/Engineering :: Physics
Requires-Dist: django (<1.9,>=1.8)
Requires-Dist: django-filter (<0.15,>=0.10)
Requires-Dist: pytz (>=0a)
Requires-Dist: humanize
Requires-Dist: pydicom (==0.9.9)
Requires-Dist: xlsxwriter
Requires-Dist: celery (<4.3,>=3.1)
Requires-Dist: argparse (>=1.2.1)
Requires-Dist: django-qsstats-magic (<=1.0.0)
Requires-Dist: python-dateutil
Requires-Dist: django-solo
Requires-Dist: django-crispy-forms
Requires-Dist: pandas
Requires-Dist: xlrd
Requires-Dist: testfixtures (>=6.0)
Requires-Dist: mock
Requires-Dist: django-js-reverse (>=0.9.1)
Requires-Dist: requests
Requires-Dist: flower
Requires-Dist: numpy
Requires-Dist: future
Requires-Dist: defusedxml
